Workbook
Name Due_date: '7. Cell Name'!$B$3
Name GrowthRate: '5. Named Formula'!XFD1/'5. Named Formula'!XFC1-1

Sheet Cover Page
C3: 10 Excel Tricks
C7: Get 10% OFF our course using coupon code EMAIL10
C9: Get our Excel for Business & Finance Course
C11: Go to Data Here
C13: Made by Career Principles Ltd.
C15: Note
C16: All content is copyright material of Career Principles Ltd.
C17: This Excel model may not be reproduced or distributed by any means, including printing, screencapturing, or any other method without the prior permission of the publisher.

Sheet 1. 3D Reference
B2: Line item | C2: Cell | D2: Spelled-out | E2: 3D reference
B3: Product revenue | C3: B3 | E3: =SUM(ES:DE!B3) -> 215000
B4: Service revenue | C4: B4 | E4: =SUM(ES:DE!B4) -> 178000
B5: Other revenue | C5: B5 | E5: =SUM(ES:DE!B5) -> 414000
B6: COGS - materials | C6: B6 | E6: =SUM(ES:DE!B6) -> 454000
B7: COGS - labour | C7: B7 | E7: =SUM(ES:DE!B7) -> 458000
B8: Salaries | C8: B8 | E8: =SUM(ES:DE!B8) -> 326000
B9: Marketing | C9: B9 | E9: =SUM(ES:DE!B9) -> 248000
B10: Rent | C10: B10 | E10: =SUM(ES:DE!B10) -> 340000
B11: Utilities | C11: B11 | E11: =SUM(ES:DE!B11) -> 334000
B12: Software | C12: B12 | E12: =SUM(ES:DE!B12) -> 373000
B13: Travel | C13: B13 | E13: =SUM(ES:DE!B13) -> 155000
B14: Insurance | C14: B14 | E14: =SUM(ES:DE!B14) -> 322000
... B16: Other opex | C16: B16 | E16: =SUM(ES:DE!B16) -> 282000

Sheet ES
A1: Spain — P&L (input)
A2: Line item | B2: Amount
A3: Product revenue | B3: 62000
A4: Service revenue | B4: 127000
A5: Other revenue | B5: 196000
A6: COGS - materials | B6: 127000
A7: COGS - labour | B7: 182000
A8: Salaries | B8: 92000
A9: Marketing | B9: 142000
A10: Rent | B10: 75000
A11: Utilities | B11: 141000
A12: Software | B12: 151000
A13: Travel | B13: 66000
A14: Insurance | B14: 149000
... A16: Other opex | B16: 80000

Sheet FR
A1: France — P&L (input)
A2: Line item | B2: Amount
A3: Product revenue | B3: 20000
A4: Service revenue | B4: 23000
A5: Other revenue | B5: 114000
A6: COGS - materials | B6: 169000
A7: COGS - labour | B7: 129000
A8: Salaries | B8: 37000
A9: Marketing | B9: 57000
A10: Rent | B10: 79000
A11: Utilities | B11: 79000
A12: Software | B12: 197000
A13: Travel | B13: 30000
A14: Insurance | B14: 131000
... A16: Other opex | B16: 177000

Sheet DE
A1: Germany — P&L (input)
A2: Line item | B2: Amount
A3: Product revenue | B3: 133000
A4: Service revenue | B4: 28000
A5: Other revenue | B5: 104000
A6: COGS - materials | B6: 158000
A7: COGS - labour | B7: 147000
A8: Salaries | B8: 197000
A9: Marketing | B9: 49000
A10: Rent | B10: 186000
A11: Utilities | B11: 114000
A12: Software | B12: 25000
A13: Travel | B13: 59000
A14: Insurance | B14: 42000
... A16: Other opex | B16: 25000

Sheet 2. Double Dash
B2: Month | C2: Region | D2: Actual | E2: Budget
B3: Jan | C3: North | D3: 137000 | E3: 125000 | G3: Months we beat the budget | H3: {=SUMPRODUCT(--(D3:D17>E3:E17))} -> 12
B4: Feb | C4: South | D4: 139000 | E4: 118000
B5: Mar | C5: East | D5: 145000 | E5: 127000
B6: Apr | C6: West | D6: 104000 | E6: 101000
B7: May | C7: North | D7: 145000 | E7: 120000
B8: Jun | C8: South | D8: 160000 | E8: 129000
B9: Jul | C9: East | D9: 103000 | E9: 96000
B10: Aug | C10: West | D10: 137000 | E10: 109000
B11: Sep | C11: North | D11: 98000 | E11: 95000
B12: Oct | C12: South | D12: 148000 | E12: 134000
B13: Nov | C13: East | D13: 85000 | E13: 128000
B14: Dec | C14: West | D14: 130000 | E14: 118000
B15: Jan | C15: North | D15: 158000 | E15: 131000
... B17: Mar | C17: East | D17: 81000 | E17: 123000

Sheet 3. Millions
B2: Business unit | C2: Revenue
B3: Cloud | C3: 586222860
B4: Hardware | C4: 576791350
B5: Services | C5: 44950980
B6: Advertising | C6: 68461510
B7: Retail | C7: 63956630
B8: Logistics | C8: 249301560
B9: Finance | C9: 567693800
B10: Media | C10: 120470090
B11: Gaming | C11: 500901090
B12: Health | C12: 549885230
B13: Auto | C13: 456448460
B14: Energy | C14: 579998550
... B18: TOTAL | C18: 5168345910

Sheet 4. Aggregate
B2: Product | C2: Revenue | D2: Units Sold | E2: Avg price
B3: Cloud Pro | C3: 30537 | D3: 783 | E3: =C3/D3 -> 39 | G3: Avg. Price | H3: =_xlfn.AGGREGATE(1,6,E3:E17) -> 35.769231
B4: Analytics | C4: 22995 | D4: 511 | E4: =C4/D4 -> 45
B5: Security | C5: 0 | D5: 0 | E5: =C5/D5 -> #DIV/0!
B6: Storage | C6: 37120 | D6: 1280 | E6: =C6/D6 -> 29
B7: Mobile | C7: 11616 | D7: 484 | E7: =C7/D7 -> 24
B8: Desktop | C8: 15300 | D8: 340 | E8: =C8/D8 -> 45
B9: API tier | C9: 54150 | D9: 1425 | E9: =C9/D9 -> 38
B10: Support | C10: 44597 | D10: 1939 | E10: =C10/D10 -> 23
B11: Training | C11: 39962 | D11: 754 | E11: =C11/D11 -> 53
B12: Add-ons | C12: 0 | D12: 0 | E12: =C12/D12 -> #DIV/0!
B13: Hardware | C13: 60157 | D13: 1399 | E13: =C13/D13 -> 43
B14: Consulting | C14: 26846 | D14: 866 | E14: =C14/D14 -> 31
B15: Partner | C15: 51818 | D15: 1993 | E15: =C15/D15 -> 26
... B17: Trial | C17: 12672 | D17: 352 | E17: =C17/D17 -> 36

Sheet 5. Named Formula
B2: Business unit | C2: Prior year | D2: This year | E2: Growth %
B3: Cloud | C3: 3749000 | D3: 4369838 | E3: {=GrowthRate} -> 0.16560096
B4: Hardware | C4: 830000 | D4: 926918 | E4: {=GrowthRate} -> 0.11676867
B5: Services | C5: 1571000 | D5: 1367166 | E5: {=GrowthRate} -> -0.12974793
B6: Advertising | C6: 1096000 | D6: 1331147 | E6: {=GrowthRate} -> 0.21455018
B7: Retail | C7: 2426000 | D7: 3350390 | E7: {=GrowthRate} -> 0.38103462
B8: Logistics | C8: 3509000 | D8: 3702830 | E8: {=GrowthRate} -> 0.05523796
B9: Finance | C9: 3654000 | D9: 3149891 | E9: {=GrowthRate} -> -0.13796086
B10: Media | C10: 2502000 | D10: 3230215 | E10: {=GrowthRate} -> 0.29105316
B11: Gaming | C11: 3489000 | D11: 4639947 | E11: {=GrowthRate} -> 0.32987876
B12: Health | C12: 2704000 | D12: 3100373 | E12: {=GrowthRate} -> 0.14658765
B13: Auto | C13: 885000 | D13: 846185 | E13: {=GrowthRate} -> -0.043858757
B14: Energy | C14: 2767000 | D14: 3416520 | E14: {=GrowthRate} -> 0.23473798
... B17: Other | C17: 860000 | D17: 1130345 | E17: {=GrowthRate} -> 0.31435465
B18: TOTAL | C18: =SUM(C3:C17) -> 37317000 | D18: =SUM(D3:D17) -> 42526095 | E18: =D18/C18-1 -> 0.1395904

Sheet 6. Cury Brackets
B2: IF Paid, Refunded, or Chargeback, then Money Moved TRUE
B4: Date | C4: Customer | D4: Amount | E4: Status | F4: Money moved?
B5: 2025-06-01 | C5: Acme Corp | D5: 1240 | E5: Paid | F5: {=OR(E5={"Paid","Refunded","Chargeback"})} -> TRUE
B6: 2025-06-01 | C6: Blue Ridge Ltd | D6: 89.99 | E6: Pending | F6: {=OR(E6={"Paid","Refunded","Chargeback"})} -> FALSE
B7: 2025-06-02 | C7: Nomura K.K. | D7: 450 | E7: Refunded | F7: {=OR(E7={"Paid","Refunded","Chargeback"})} -> TRUE
B8: 2025-06-02 | C8: Delgado SL | D8: 32.5 | E8: Failed | F8: {=OR(E8={"Paid","Refunded","Chargeback"})} -> FALSE
B9: 2025-06-03 | C9: Hopewell Inc | D9: 2100 | E9: Paid | F9: {=OR(E9={"Paid","Refunded","Chargeback"})} -> TRUE
B10: 2025-06-03 | C10: Sunmark GmbH | D10: 675 | E10: Chargeback | F10: {=OR(E10={"Paid","Refunded","Chargeback"})} -> TRUE
B11: 2025-06-04 | C11: Verity LLC | D11: 199 | E11: Authorized | F11: {=OR(E11={"Paid","Refunded","Chargeback"})} -> FALSE
B12: 2025-06-04 | C12: Acme Corp | D12: 540 | E12: Paid | F12: {=OR(E12={"Paid","Refunded","Chargeback"})} -> TRUE
B13: 2025-06-05 | C13: Kestrel Co | D13: 78.25 | E13: Pending | F13: {=OR(E13={"Paid","Refunded","Chargeback"})} -> FALSE
B14: 2025-06-05 | C14: Blue Ridge Ltd | D14: 120 | E14: Refunded | F14: {=OR(E14={"Paid","Refunded","Chargeback"})} -> TRUE
B15: 2025-06-06 | C15: Tanaka Trading | D15: 15.99 | E15: Failed | F15: {=OR(E15={"Paid","Refunded","Chargeback"})} -> FALSE
B16: 2025-06-06 | C16: Orchard Partners | D16: 3320 | E16: Paid | F16: {=OR(E16={"Paid","Refunded","Chargeback"})} -> TRUE
... B19: 2025-06-08 | C19: Hopewell Inc | D19: 960 | E19: Paid | F19: {=OR(E19={"Paid","Refunded","Chargeback"})} -> TRUE

Sheet 7. Cell Name
B2: Due Date | C2: +7 Days | D2: +14 Days | E2: +30 Days
B3: 46388 | C3: {=Due_date+{7,14,30}} -> 46395 | D3: 46402 | E3: 46418

Sheet 8. Dot Operator
B2: Product | C2: Revenue | D2: Costs | E2: Profit | H2: Quarter | I2: Revenue | K2: Quarter | L2: Revenue | N2: Quarter | O2: Total Revenue
B3: Printer | C3: 3000 | D3: 1800 | E3: {=C3:C9-D3:D9} -> 1200 | H3: Q1 | I3: 3000 | K3: Q2 | L3: 4200
B4: Scanner | C4: 1500 | D4: 825 | E4: 675 | H4: Q1 | I4: 1500 | K4: Q2 | L4: 2100
B5: Laptop | C5: 1800 | D5: 900 | E5: 900 | H5: Q1 | I5: 1800 | K5: Q2 | L5: 2520
B6: Projector | C6: 3375 | D6: 2025 | E6: 1350 | H6: Q1 | I6: 3375 | K6: Q2 | L6: 4725
B7: Whiteboard | C7: 1600 | D7: 880 | E7: 720 | H7: Q1 | I7: 1600 | K7: Q2 | L7: 2240
B8: Desk Lamp | C8: 1900 | D8: 950 | E8: 950 | H8: Q1 | I8: 1900 | K8: Q2 | L8: 2660
B9: Chair | C9: 2400 | D9: 1200 | E9: 1200 | H9: Q1 | I9: 2400 | K9: Q2 | L9: 3360

Sheet 9. Arrows
B2: Business unit | C2: Prior year | D2: This year | E2: Growth % | G2: Arrow Formatting: | H2: ▲0.0%;[Red]▼0.0%;0.0%
B3: Cloud | C3: 3749000 | D3: 4369838 | E3: =D3/C3-1 -> 0.16560096
B4: Hardware | C4: 830000 | D4: 926918 | E4: =D4/C4-1 -> 0.11676867
B5: Services | C5: 1571000 | D5: 1367166 | E5: =D5/C5-1 -> -0.12974793
B6: Advertising | C6: 1096000 | D6: 1331147 | E6: =D6/C6-1 -> 0.21455018
B7: Retail | C7: 2426000 | D7: 3350390 | E7: =D7/C7-1 -> 0.38103462
B8: Logistics | C8: 3509000 | D8: 3702830 | E8: =D8/C8-1 -> 0.05523796
B9: Finance | C9: 3654000 | D9: 3149891 | E9: =D9/C9-1 -> -0.13796086
B10: Media | C10: 2502000 | D10: 3230215 | E10: =D10/C10-1 -> 0.29105316
B11: Gaming | C11: 3489000 | D11: 4639947 | E11: =D11/C11-1 -> 0.32987876
B12: Health | C12: 2704000 | D12: 3100373 | E12: =D12/C12-1 -> 0.14658765
B13: Auto | C13: 885000 | D13: 846185 | E13: =D13/C13-1 -> -0.043858757
B14: Energy | C14: 2767000 | D14: 3416520 | E14: =D14/C14-1 -> 0.23473798
... B17: Other | C17: 860000 | D17: 1130345 | E17: =D17/C17-1 -> 0.31435465

Sheet 10. Navigation
